fastmcp_agents/library/mcp/__init__.py
fastmcp_agents/library/mcp/github/__init__.py
fastmcp_agents/library/mcp/github/github.py
fastmcp_agents/library/mcp/motherduck/__init__.py
fastmcp_agents/library/mcp/motherduck/duckdb.py
fastmcp_agents/library/mcp/nickclyde/__init__.py
fastmcp_agents/library/mcp/nickclyde/duckduckgo.py
fastmcp_agents/library/mcp/strawgate/__init__.py
fastmcp_agents/library/mcp/strawgate/elasticsearch.py
fastmcp_agents/library/mcp/strawgate/filesystem_operations.py
fastmcp_agents/library/mcp/strawgate/knowledge_base.py
fastmcp_agents/library/mcp/wrale/tree_sitter.py
fastmcp_agents_library_mcp-0.5.10.dist-info/WHEEL
fastmcp_agents_library_mcp-0.5.10.dist-info/METADATA
fastmcp_agents_library_mcp-0.5.10.dist-info/RECORD
