Metadata-Version: 2.3
Name: fastmcp-agents-library-mcp
Version: 0.5.10
Summary: MCP Library for FastMCP Agents
Requires-Dist: fastmcp
Requires-Python: >=3.13
